{"name":"build-javascript","namedChunkGroups":{"app":{"name":"app","assets":[{"name":"webpack-runtime-3f300bd8c630b14de347.js","size":5052},{"name":"framework-e1920fffb1cf79c01553.js","size":140793},{"name":"app-7e4cdca9b83f07428514.js","size":92709}],"filteredAssets":0,"assetsSize":238554,"filteredAuxiliaryAssets":3,"auxiliaryAssetsSize":720381},"component---src-pages-404-js":{"name":"component---src-pages-404-js","assets":[{"name":"styles.c8b20ab45f528787af2f.css","size":11810},{"name":"cb355538-b7f8b399160e06be65f4.js","size":740},{"name":"component---src-pages-404-js-1d9fda98c530997810f3.js","size":4403}],"filteredAssets":0,"assetsSize":16953,"filteredAuxiliaryAssets":3,"auxiliaryAssetsSize":1440040},"component---src-pages-about-js":{"name":"component---src-pages-about-js","assets":[{"name":"styles.c8b20ab45f528787af2f.css","size":11810},{"name":"cb355538-b7f8b399160e06be65f4.js","size":740},{"name":"component---src-pages-about-js-db7455cd4852570e4854.js","size":4300}],"filteredAssets":0,"assetsSize":16850,"filteredAuxiliaryAssets":3,"auxiliaryAssetsSize":1439858},"component---src-pages-contact-js":{"name":"component---src-pages-contact-js","assets":[{"name":"styles.c8b20ab45f528787af2f.css","size":11810},{"name":"cb355538-b7f8b399160e06be65f4.js","size":740},{"name":"component---src-pages-contact-js-be3fc6c439667ea15231.js","size":5757}],"filteredAssets":0,"assetsSize":18307,"filteredAuxiliaryAssets":3,"auxiliaryAssetsSize":1442431},"component---src-pages-index-js":{"name":"component---src-pages-index-js","assets":[{"name":"styles.c8b20ab45f528787af2f.css","size":11810},{"name":"cb355538-b7f8b399160e06be65f4.js","size":740},{"name":"component---src-pages-index-js-250cc36fffa04d0dac87.js","size":4343}],"filteredAssets":0,"assetsSize":16893,"filteredAuxiliaryAssets":3,"auxiliaryAssetsSize":1439890},"component---src-pages-recipes-js":{"name":"component---src-pages-recipes-js","assets":[{"name":"styles.c8b20ab45f528787af2f.css","size":11810},{"name":"cb355538-b7f8b399160e06be65f4.js","size":740},{"name":"component---src-pages-recipes-js-6457362edb9a0d39701c.js","size":4304}],"filteredAssets":0,"assetsSize":16854,"filteredAuxiliaryAssets":3,"auxiliaryAssetsSize":1439871},"component---src-pages-tags-js":{"name":"component---src-pages-tags-js","assets":[{"name":"styles.c8b20ab45f528787af2f.css","size":11810},{"name":"cb355538-b7f8b399160e06be65f4.js","size":740},{"name":"component---src-pages-tags-js-4de82f139adcc8cce338.js","size":4298}],"filteredAssets":0,"assetsSize":16848,"filteredAuxiliaryAssets":3,"auxiliaryAssetsSize":1439852}},"assetsByChunkName":{"app":["webpack-runtime-3f300bd8c630b14de347.js","framework-e1920fffb1cf79c01553.js","app-7e4cdca9b83f07428514.js"],"component---src-pages-404-js":["styles.c8b20ab45f528787af2f.css","cb355538-b7f8b399160e06be65f4.js","component---src-pages-404-js-1d9fda98c530997810f3.js"],"component---src-pages-about-js":["styles.c8b20ab45f528787af2f.css","cb355538-b7f8b399160e06be65f4.js","component---src-pages-about-js-db7455cd4852570e4854.js"],"component---src-pages-contact-js":["styles.c8b20ab45f528787af2f.css","cb355538-b7f8b399160e06be65f4.js","component---src-pages-contact-js-be3fc6c439667ea15231.js"],"component---src-pages-index-js":["styles.c8b20ab45f528787af2f.css","cb355538-b7f8b399160e06be65f4.js","component---src-pages-index-js-250cc36fffa04d0dac87.js"],"component---src-pages-recipes-js":["styles.c8b20ab45f528787af2f.css","cb355538-b7f8b399160e06be65f4.js","component---src-pages-recipes-js-6457362edb9a0d39701c.js"],"component---src-pages-tags-js":["styles.c8b20ab45f528787af2f.css","cb355538-b7f8b399160e06be65f4.js","component---src-pages-tags-js-4de82f139adcc8cce338.js"]},"childAssetsByChunkName":{}}